daml_rag/__init__.py
daml_rag/base.py
daml_rag/core.py
daml_rag/adapters/__init__.py
daml_rag/adapters/base/__init__.py
daml_rag/adapters/base/adapter.py
daml_rag/adapters/fitness/__init__.py
daml_rag/adapters/fitness/fitness_adapter.py
daml_rag/cli/__init__.py
daml_rag/cli/cli.py
daml_rag/cli/commands/__init__.py
daml_rag/cli/commands/init.py
daml_rag/config/__init__.py
daml_rag/config/framework_config.py
daml_rag/interfaces/__init__.py
daml_rag/interfaces/learning.py
daml_rag/interfaces/orchestration.py
daml_rag/interfaces/retrieval.py
daml_rag/learning/__init__.py
daml_rag/learning/adaptation.py
daml_rag/learning/feedback.py
daml_rag/learning/memory.py
daml_rag/learning/model_provider.py
daml_rag/learning/query_classifier.py
daml_rag/learning/tool_learner_thompson.py
daml_rag/models/__init__.py
daml_rag/models/base.py
daml_rag/orchestration/__init__.py
daml_rag/orchestration/mcp_orchestrator.py
daml_rag/orchestration/orchestrator.py
daml_rag/retrieval/__init__.py
daml_rag/retrieval/embedding.py
daml_rag/retrieval/three_tier.py
daml_rag/retrieval/vector.py
daml_rag/retrieval/knowledge/__init__.py
daml_rag/retrieval/knowledge/neo4j.py
daml_rag/retrieval/rules/__init__.py
daml_rag/retrieval/rules/engine.py
daml_rag/retrieval/vector/__init__.py
daml_rag/retrieval/vector/base.py
daml_rag/retrieval/vector/faiss.py
daml_rag/retrieval/vector/qdrant.py
daml_rag_framework-1.3.0.dist-info/licenses/LICENSE
daml_rag_framework-1.3.0.dist-info/licenses/NOTICE
daml_rag_framework-1.3.0.dist-info/METADATA
daml_rag_framework-1.3.0.dist-info/WHEEL
daml_rag_framework-1.3.0.dist-info/entry_points.txt
daml_rag_framework-1.3.0.dist-info/top_level.txt
daml_rag_framework-1.3.0.dist-info/RECORD
