Metadata-Version: 2.4
Name: daml-rag-framework
Version: 1.3.0
Summary: Domain-Adaptive Meta-Learning RAG Framework for Vertical Domain AI Applications
Author-email: "薛小川 (Xue Xiaochuan)" <1765563156@qq.com>
Maintainer-email: "薛小川 (Xue Xiaochuan)" <1765563156@qq.com>
License: Apache-2.0
Project-URL: Homepage, https://github.com/vivy1024/daml-rag-framework
Project-URL: Documentation, https://github.com/vivy1024/daml-rag-framework/tree/main/docs
Project-URL: Repository, https://github.com/vivy1024/daml-rag-framework
Project-URL: Bug Tracker, https://github.com/vivy1024/daml-rag-framework/issues
Project-URL: Changelog, https://github.com/vivy1024/daml-rag-framework/blob/main/CHANGELOG.md
Project-URL: Theory Evolution, https://github.com/vivy1024/daml-rag-framework/blob/main/docs/theory/00-THEORY_EVOLUTION.md
Project-URL: References, https://github.com/vivy1024/daml-rag-framework/blob/main/REFERENCES.md
Keywords: rag,retrieval-augmented-generation,graphrag,knowledge-graph,artificial-intelligence,machine-learning,in-context-learning,multi-agent-systems,vertical-domain,production-ready,vector-database,neo4j,qdrant,mcp,model-context-protocol
Classifier: Development Status :: 4 - Beta
Classifier: Intended Audience :: Developers
Classifier: Intended Audience :: Science/Research
Classifier: Topic :: Scientific/Engineering :: Artificial Intelligence
Classifier: Topic :: Software Development :: Libraries :: Python Modules
Classifier: License :: OSI Approved :: Apache Software License
Classifier: Programming Language :: Python :: 3
Classifier: Programming Language :: Python :: 3.8
Classifier: Programming Language :: Python :: 3.9
Classifier: Programming Language :: Python :: 3.10
Classifier: Programming Language :: Python :: 3.11
Classifier: Programming Language :: Python :: 3.12
Classifier: Operating System :: OS Independent
Requires-Python: >=3.8
License-File: LICENSE
License-File: NOTICE
Requires-Dist: fastapi>=0.104.0
Requires-Dist: uvicorn[standard]>=0.24.0
Requires-Dist: pydantic>=2.0.0
Requires-Dist: pydantic-settings>=2.0.0
Requires-Dist: httpx>=0.25.0
Requires-Dist: aiohttp>=3.9.0
Requires-Dist: python-multipart>=0.0.6
Requires-Dist: python-jose[cryptography]>=3.3.0
Requires-Dist: passlib[bcrypt]>=1.7.4
Requires-Dist: qdrant-client>=1.7.0
Requires-Dist: neo4j>=5.14.0
Requires-Dist: sentence-transformers>=2.2.0
Requires-Dist: torch>=2.0.0
Requires-Dist: transformers>=4.35.0
Requires-Dist: numpy>=1.24.0
Requires-Dist: pandas>=2.0.0
Requires-Dist: redis>=5.0.0
Requires-Dist: python-dotenv>=1.0.0
Requires-Dist: pyyaml>=6.0
Requires-Dist: loguru>=0.7.0
Provides-Extra: dev
Requires-Dist: pytest>=7.4.0; extra == "dev"
Requires-Dist: pytest-asyncio>=0.21.0; extra == "dev"
Requires-Dist: pytest-cov>=4.1.0; extra == "dev"
Requires-Dist: black>=23.0.0; extra == "dev"
Requires-Dist: isort>=5.12.0; extra == "dev"
Requires-Dist: flake8>=6.1.0; extra == "dev"
Requires-Dist: mypy>=1.5.0; extra == "dev"
Requires-Dist: pre-commit>=3.4.0; extra == "dev"
Provides-Extra: docs
Requires-Dist: mkdocs>=1.5.0; extra == "docs"
Requires-Dist: mkdocs-material>=9.4.0; extra == "docs"
Requires-Dist: mkdocstrings[python]>=0.23.0; extra == "docs"
Provides-Extra: all
Requires-Dist: daml-rag-framework[dev,docs]; extra == "all"
Dynamic: license-file
